{
  "student_id": "Sample_Student",
  "worksheet_id": "WS5",
  "evidence_units": [
    {
      "item_id": "WS5_B1",
      "evidence_unit_type": "model_evaluation",
      "evidence_completeness": "complete",
      "content": "şeker ≤ 5",
      "confidence": {
        "extraction": 0.85,
        "evidence_quality": 0.82
      }
    },
    {
      "item_id": "WS5_B10",
      "evidence_unit_type": "model_evaluation",
      "evidence_completeness": "complete",
      "content": "8",
      "confidence": {
        "extraction": 0.85,
        "evidence_quality": 0.82
      }
    },
    {
      "item_id": "WS5_B11",
      "evidence_unit_type": "model_evaluation",
      "evidence_completeness": "complete",
      "content": "2",
      "confidence": {
        "extraction": 0.85,
        "evidence_quality": 0.82
      }
    },
    {
      "item_id": "WS5_B12",
      "evidence_unit_type": "model_evaluation",
      "evidence_completeness": "complete",
      "content": "0.20",
      "confidence": {
        "extraction": 0.85,
        "evidence_quality": 0.82
      }
    },
    {
      "item_id": "WS5_B13",
      "evidence_unit_type": "model_evaluation",
      "evidence_completeness": "complete",
      "content": "şeker ≤ 12",
      "confidence": {
        "extraction": 0.85,
        "evidence_quality": 0.82
      }
    },
    {
      "item_id": "WS5_B14",
      "evidence_unit_type": "model_evaluation",
      "evidence_completeness": "complete",
      "content": "9",
      "confidence": {
        "extraction": 0.85,
        "evidence_quality": 0.82
      }
    },
    {
      "item_id": "WS5_B15",
      "evidence_unit_type": "model_evaluation",
      "evidence_completeness": "complete",
      "content": "1",
      "confidence": {
        "extraction": 0.85,
        "evidence_quality": 0.82
      }
    },
    {
      "item_id": "WS5_B16",
      "evidence_unit_type": "model_evaluation",
      "evidence_completeness": "complete",
      "content": "0.20",
      "confidence": {
        "extraction": 0.85,
        "evidence_quality": 0.82
      }
    },
    {
      "item_id": "WS5_B17",
      "evidence_unit_type": "model_evaluation",
      "evidence_completeness": "complete",
      "content": "şeker ≤ 15",
      "confidence": {
        "extraction": 0.85,
        "evidence_quality": 0.82
      }
    },
    {
      "item_id": "WS5_B18",
      "evidence_unit_type": "model_evaluation",
      "evidence_completeness": "complete",
      "content": "10",
      "confidence": {
        "extraction": 0.85,
        "evidence_quality": 0.82
      }
    },
    {
      "item_id": "WS5_B19",
      "evidence_unit_type": "model_evaluation",
      "evidence_completeness": "complete",
      "content": "0",
      "confidence": {
        "extraction": 0.85,
        "evidence_quality": 0.82
      }
    },
    {
      "item_id": "WS5_B2",
      "evidence_unit_type": "model_evaluation",
      "evidence_completeness": "complete",
      "content": "3",
      "confidence": {
        "extraction": 0.85,
        "evidence_quality": 0.82
      }
    },
    {
      "item_id": "WS5_B20",
      "evidence_unit_type": "model_evaluation",
      "evidence_completeness": "complete",
      "content": "0.25",
      "confidence": {
        "extraction": 0.85,
        "evidence_quality": 0.82
      }
    },
    {
      "item_id": "WS5_B21",
      "evidence_unit_type": "model_evaluation",
      "evidence_completeness": "blank",
      "content": "(bos)",
      "confidence": {
        "extraction": 0.35,
        "evidence_quality": 0.212
      }
    },
    {
      "item_id": "WS5_B22",
      "evidence_unit_type": "model_evaluation",
      "evidence_completeness": "blank",
      "content": "(bos)",
      "confidence": {
        "extraction": 0.35,
        "evidence_quality": 0.212
      }
    },
    {
      "item_id": "WS5_B23",
      "evidence_unit_type": "model_evaluation",
      "evidence_completeness": "blank",
      "content": "(bos)",
      "confidence": {
        "extraction": 0.35,
        "evidence_quality": 0.212
      }
    },
    {
      "item_id": "WS5_B24",
      "evidence_unit_type": "model_evaluation",
      "evidence_completeness": "blank",
      "content": "(bos)",
      "confidence": {
        "extraction": 0.35,
        "evidence_quality": 0.212
      }
    },
    {
      "item_id": "WS5_B25",
      "evidence_unit_type": "comparison",
      "evidence_completeness": "complete",
      "content": "Eşik 8, 10 ve 12 aynı MCR'yi veriyor. En küçük eşik değeri olan 8'i tercih ederim.",
      "confidence": {
        "extraction": 0.85,
        "evidence_quality": 0.82
      }
    },
    {
      "item_id": "WS5_B3",
      "evidence_unit_type": "model_evaluation",
      "evidence_completeness": "complete",
      "content": "7",
      "confidence": {
        "extraction": 0.85,
        "evidence_quality": 0.82
      }
    },
    {
      "item_id": "WS5_B4",
      "evidence_unit_type": "model_evaluation",
      "evidence_completeness": "complete",
      "content": "0.30",
      "confidence": {
        "extraction": 0.85,
        "evidence_quality": 0.82
      }
    },
    {
      "item_id": "WS5_B5",
      "evidence_unit_type": "model_evaluation",
      "evidence_completeness": "complete",
      "content": "şeker ≤ 8",
      "confidence": {
        "extraction": 0.85,
        "evidence_quality": 0.82
      }
    },
    {
      "item_id": "WS5_B6",
      "evidence_unit_type": "model_evaluation",
      "evidence_completeness": "complete",
      "content": "5",
      "confidence": {
        "extraction": 0.85,
        "evidence_quality": 0.82
      }
    },
    {
      "item_id": "WS5_B7",
      "evidence_unit_type": "model_evaluation",
      "evidence_completeness": "complete",
      "content": "5",
      "confidence": {
        "extraction": 0.85,
        "evidence_quality": 0.82
      }
    },
    {
      "item_id": "WS5_B8",
      "evidence_unit_type": "model_evaluation",
      "evidence_completeness": "complete",
      "content": "0.20",
      "confidence": {
        "extraction": 0.85,
        "evidence_quality": 0.82
      }
    },
    {
      "item_id": "WS5_B9",
      "evidence_unit_type": "model_evaluation",
      "evidence_completeness": "complete",
      "content": "şeker ≤ 10",
      "confidence": {
        "extraction": 0.85,
        "evidence_quality": 0.82
      }
    }
  ]
}
